Workbook

Sheet Dashboard
A1: Shop Sales Dashboard
A3: Total Sales | B3: =SUM('Raw Data'!$G$2:$G$301) -> 1195595
A4: Total Orders | B4: =COUNTA('Raw Data'!$A$2:$A$301) -> 300
A5: Average Order Value | B5: =SUM('Raw Data'!$G$2:$G$301)/COUNTA('Raw Data'!$A$2:$A$301) -> 3985.3167
A6: Best-Selling Category | B6: =INDEX(Analysis!A5:A10,MATCH(MAX(Analysis!B5:B10),Analysis!B5:B10,0)) -> Furniture
A9: Data source: Raw Data sheet (synthetic shop transactions, Jan-Dec 2025)

Sheet Price Lookup
A1: Product | B1: Category | C1: Unit Price
A2: Wireless Mouse | B2: Electronics | C2: 599
A3: Bluetooth Speaker | B3: Electronics | C3: 1499
A4: USB Cable | B4: Electronics | C4: 149
A5: Notebook | B5: Stationery | C5: 60
A6: Ball Pen (Pack of 5) | B6: Stationery | C6: 40
A7: Sketch Pens | B7: Stationery | C7: 90
A8: Office Chair | B8: Furniture | C8: 3499
A9: Study Table | B9: Furniture | C9: 2999
A10: LED Desk Lamp | B10: Furniture | C10: 799
A11: Water Bottle | B11: Home & Kitchen | C11: 199
A12: Steel Tiffin Box | B12: Home & Kitchen | C12: 349
A13: Non-stick Pan | B13: Home & Kitchen | C13: 899
... A19: Hand Sanitizer | B19: Personal Care | C19: 99

Sheet Raw Data
A1: Order ID | B1: Date | C1: Product | D1: Category | E1: Unit Price | F1: Quantity | G1: Total Sales | H1: Region | I1: Payment Mode
A2: ORD1001 | B2: 45985 | C2: Notebook | D2: =INDEX('Price Lookup'!$B$2:$B$19,MATCH(C2,'Price Lookup'!$A$2:$A$19,0)) -> Stationery | E2: =INDEX('Price Lookup'!$C$2:$C$19,MATCH(C2,'Price Lookup'!$A$2:$A$19,0)) -> 60 | F2: 1 | G2: =E2*F2 -> 60 | H2: East | I2: UPI
A3: ORD1002 | B3: 45772 | C3: Ball Pen (Pack of 5) | D3: =INDEX('Price Lookup'!$B$2:$B$19,MATCH(C3,'Price Lookup'!$A$2:$A$19,0)) -> Stationery | E3: =INDEX('Price Lookup'!$C$2:$C$19,MATCH(C3,'Price Lookup'!$A$2:$A$19,0)) -> 40 | F3: 2 | G3: =E3*F3 -> 80 | H3: North | I3: Net Banking
A4: ORD1003 | B4: 45674 | C4: Wireless Mouse | D4: =INDEX('Price Lookup'!$B$2:$B$19,MATCH(C4,'Price Lookup'!$A$2:$A$19,0)) -> Electronics | E4: =INDEX('Price Lookup'!$C$2:$C$19,MATCH(C4,'Price Lookup'!$A$2:$A$19,0)) -> 599 | F4: 2 | G4: =E4*F4 -> 1198 | H4: South | I4: UPI
A5: ORD1004 | B5: 45916 | C5: Wireless Mouse | D5: =INDEX('Price Lookup'!$B$2:$B$19,MATCH(C5,'Price Lookup'!$A$2:$A$19,0)) -> Electronics | E5: =INDEX('Price Lookup'!$C$2:$C$19,MATCH(C5,'Price Lookup'!$A$2:$A$19,0)) -> 599 | F5: 4 | G5: =E5*F5 -> 2396 | H5: West | I5: UPI
A6: ORD1005 | B6: 45887 | C6: LED Desk Lamp | D6: =INDEX('Price Lookup'!$B$2:$B$19,MATCH(C6,'Price Lookup'!$A$2:$A$19,0)) -> Furniture | E6: =INDEX('Price Lookup'!$C$2:$C$19,MATCH(C6,'Price Lookup'!$A$2:$A$19,0)) -> 799 | F6: 1 | G6: =E6*F6 -> 799 | H6: South | I6: Net Banking
A7: ORD1006 | B7: 45832 | C7: LED Desk Lamp | D7: =INDEX('Price Lookup'!$B$2:$B$19,MATCH(C7,'Price Lookup'!$A$2:$A$19,0)) -> Furniture | E7: =INDEX('Price Lookup'!$C$2:$C$19,MATCH(C7,'Price Lookup'!$A$2:$A$19,0)) -> 799 | F7: 3 | G7: =E7*F7 -> 2397 | H7: South | I7: Card
A8: ORD1007 | B8: 45710 | C8: USB Cable | D8: =INDEX('Price Lookup'!$B$2:$B$19,MATCH(C8,'Price Lookup'!$A$2:$A$19,0)) -> Electronics | E8: =INDEX('Price Lookup'!$C$2:$C$19,MATCH(C8,'Price Lookup'!$A$2:$A$19,0)) -> 149 | F8: 7 | G8: =E8*F8 -> 1043 | H8: North | I8: Card
A9: ORD1008 | B9: 45834 | C9: LED Desk Lamp | D9: =INDEX('Price Lookup'!$B$2:$B$19,MATCH(C9,'Price Lookup'!$A$2:$A$19,0)) -> Furniture | E9: =INDEX('Price Lookup'!$C$2:$C$19,MATCH(C9,'Price Lookup'!$A$2:$A$19,0)) -> 799 | F9: 1 | G9: =E9*F9 -> 799 | H9: West | I9: Cash
A10: ORD1009 | B10: 45851 | C10: USB Cable | D10: =INDEX('Price Lookup'!$B$2:$B$19,MATCH(C10,'Price Lookup'!$A$2:$A$19,0)) -> Electronics | E10: =INDEX('Price Lookup'!$C$2:$C$19,MATCH(C10,'Price Lookup'!$A$2:$A$19,0)) -> 149 | F10: 5 | G10: =E10*F10 -> 745 | H10: East | I10: UPI
A11: ORD1010 | B11: 46018 | C11: USB Cable | D11: =INDEX('Price Lookup'!$B$2:$B$19,MATCH(C11,'Price Lookup'!$A$2:$A$19,0)) -> Electronics | E11: =INDEX('Price Lookup'!$C$2:$C$19,MATCH(C11,'Price Lookup'!$A$2:$A$19,0)) -> 149 | F11: 1 | G11: =E11*F11 -> 149 | H11: South | I11: Card
A12: ORD1011 | B12: 45698 | C12: Study Table | D12: =INDEX('Price Lookup'!$B$2:$B$19,MATCH(C12,'Price Lookup'!$A$2:$A$19,0)) -> Furniture | E12: =INDEX('Price Lookup'!$C$2:$C$19,MATCH(C12,'Price Lookup'!$A$2:$A$19,0)) -> 2999 | F12: 2 | G12: =E12*F12 -> 5998 | H12: West | I12: Card
A13: ORD1012 | B13: 45890 | C13: Non-stick Pan | D13: =INDEX('Price Lookup'!$B$2:$B$19,MATCH(C13,'Price Lookup'!$A$2:$A$19,0)) -> Home & Kitchen | E13: =INDEX('Price Lookup'!$C$2:$C$19,MATCH(C13,'Price Lookup'!$A$2:$A$19,0)) -> 899 | F13: 3 | G13: =E13*F13 -> 2697 | H13: East | I13: Card
... A301: ORD1300 | B301: 45671 | C301: Jeans | D301: =INDEX('Price Lookup'!$B$2:$B$19,MATCH(C301,'Price Lookup'!$A$2:$A$19,0)) -> Apparel | E301: =INDEX('Price Lookup'!$C$2:$C$19,MATCH(C301,'Price Lookup'!$A$2:$A$19,0)) -> 1299 | F301: 1 | G301: =E301*F301 -> 1299 | H301: West | I301: Card

Sheet Analysis
A1: Shop Sales Analysis
A3: Sales by Category | D3: Sales by Region | G3: Sales by Payment Mode
A4: Category | B4: Total Sales | D4: Region | E4: Total Sales | G4: Payment Mode | H4: Total Sales
A5: Apparel | B5: =SUMIFS('Raw Data'!$G$2:$G$301,'Raw Data'!$D$2:$D$301,A5) -> 206554 | D5: North | E5: =SUMIFS('Raw Data'!$G$2:$G$301,'Raw Data'!$H$2:$H$301,D5) -> 233917 | G5: Cash | H5: =SUMIFS('Raw Data'!$G$2:$G$301,'Raw Data'!$I$2:$I$301,G5) -> 281666
A6: Electronics | B6: =SUMIFS('Raw Data'!$G$2:$G$301,'Raw Data'!$D$2:$D$301,A6) -> 140196 | D6: South | E6: =SUMIFS('Raw Data'!$G$2:$G$301,'Raw Data'!$H$2:$H$301,D6) -> 405976 | G6: UPI | H6: =SUMIFS('Raw Data'!$G$2:$G$301,'Raw Data'!$I$2:$I$301,G6) -> 280038
A7: Furniture | B7: =SUMIFS('Raw Data'!$G$2:$G$301,'Raw Data'!$D$2:$D$301,A7) -> 713713 | D7: East | E7: =SUMIFS('Raw Data'!$G$2:$G$301,'Raw Data'!$H$2:$H$301,D7) -> 248941 | G7: Card | H7: =SUMIFS('Raw Data'!$G$2:$G$301,'Raw Data'!$I$2:$I$301,G7) -> 367784
A8: Home & Kitchen | B8: =SUMIFS('Raw Data'!$G$2:$G$301,'Raw Data'!$D$2:$D$301,A8) -> 90655 | D8: West | E8: =SUMIFS('Raw Data'!$G$2:$G$301,'Raw Data'!$H$2:$H$301,D8) -> 306761 | G8: Net Banking | H8: =SUMIFS('Raw Data'!$G$2:$G$301,'Raw Data'!$I$2:$I$301,G8) -> 266107
A9: Personal Care | B9: =SUMIFS('Raw Data'!$G$2:$G$301,'Raw Data'!$D$2:$D$301,A9) -> 31967
A10: Stationery | B10: =SUMIFS('Raw Data'!$G$2:$G$301,'Raw Data'!$D$2:$D$301,A10) -> 12510
A12: Monthly Sales Trend
A13: Month | B13: Total Sales
A14: Jan | B14: =SUMIFS('Raw Data'!$G$2:$G$301,'Raw Data'!$B$2:$B$301,">="&DATE(2025,1,1),'Raw Data'!$B$2:$B$301,"<"&DATE(2025,2,1)) -> 78564
A15: Feb | B15: =SUMIFS('Raw Data'!$G$2:$G$301,'Raw Data'!$B$2:$B$301,">="&DATE(2025,2,1),'Raw Data'!$B$2:$B$301,"<"&DATE(2025,3,1)) -> 133757
A16: Mar | B16: =SUMIFS('Raw Data'!$G$2:$G$301,'Raw Data'!$B$2:$B$301,">="&DATE(2025,3,1),'Raw Data'!$B$2:$B$301,"<"&DATE(2025,4,1)) -> 49852
A17: Apr | B17: =SUMIFS('Raw Data'!$G$2:$G$301,'Raw Data'!$B$2:$B$301,">="&DATE(2025,4,1),'Raw Data'!$B$2:$B$301,"<"&DATE(2025,5,1)) -> 120521
A18: May | B18: =SUMIFS('Raw Data'!$G$2:$G$301,'Raw Data'!$B$2:$B$301,">="&DATE(2025,5,1),'Raw Data'!$B$2:$B$301,"<"&DATE(2025,6,1)) -> 129517
A19: Jun | B19: =SUMIFS('Raw Data'!$G$2:$G$301,'Raw Data'!$B$2:$B$301,">="&DATE(2025,6,1),'Raw Data'!$B$2:$B$301,"<"&DATE(2025,7,1)) -> 104548
A20: Jul | B20: =SUMIFS('Raw Data'!$G$2:$G$301,'Raw Data'!$B$2:$B$301,">="&DATE(2025,7,1),'Raw Data'!$B$2:$B$301,"<"&DATE(2025,8,1)) -> 96132
A21: Aug | B21: =SUMIFS('Raw Data'!$G$2:$G$301,'Raw Data'!$B$2:$B$301,">="&DATE(2025,8,1),'Raw Data'!$B$2:$B$301,"<"&DATE(2025,9,1)) -> 86726
A22: Sep | B22: =SUMIFS('Raw Data'!$G$2:$G$301,'Raw Data'!$B$2:$B$301,">="&DATE(2025,9,1),'Raw Data'!$B$2:$B$301,"<"&DATE(2025,10,1)) -> 81978
A23: Oct | B23: =SUMIFS('Raw Data'!$G$2:$G$301,'Raw Data'!$B$2:$B$301,">="&DATE(2025,10,1),'Raw Data'!$B$2:$B$301,"<"&DATE(2025,11,1)) -> 127574
A24: Nov | B24: =SUMIFS('Raw Data'!$G$2:$G$301,'Raw Data'!$B$2:$B$301,">="&DATE(2025,11,1),'Raw Data'!$B$2:$B$301,"<"&DATE(2025,12,1)) -> 75852
A25: Dec | B25: =SUMIFS('Raw Data'!$G$2:$G$301,'Raw Data'!$B$2:$B$301,">="&DATE(2025,12,1),'Raw Data'!$B$2:$B$301,"<"&DATE(2025,13,1)) -> 110574
A27: Top 5 Products by Quantity Sold
A28: Product | B28: Total Qty Sold
A29: Study Table | B29: =SUMIFS('Raw Data'!$F$2:$F$301,'Raw Data'!$C$2:$C$301,A29) -> 122
A30: Jeans | B30: =SUMIFS('Raw Data'!$F$2:$F$301,'Raw Data'!$C$2:$C$301,A30) -> 121
A31: LED Desk Lamp | B31: =SUMIFS('Raw Data'!$F$2:$F$301,'Raw Data'!$C$2:$C$301,A31) -> 85
A32: Hand Sanitizer | B32: =SUMIFS('Raw Data'!$F$2:$F$301,'Raw Data'!$C$2:$C$301,A32) -> 85
A33: Notebook | B33: =SUMIFS('Raw Data'!$F$2:$F$301,'Raw Data'!$C$2:$C$301,A33) -> 82
